{"dependencies":[{"name":"./files\\bg.jpg","dynamic":true,"loc":{"line":2,"column":5}},{"name":"_css_loader"}],"generated":{"css":"html { \r\n    background: url(d4ca4a75be7e7205cd12a642023d7f62.jpg) no-repeat center center fixed; \r\n    -webkit-background-size: cover;\r\n    -moz-background-size: cover;\r\n    -o-background-size: cover;\r\n    background-size: cover;\r\n  }\r\n  button{\r\n    height: 70px;\r\n    width: 70px;\r\n    background-color: black;\r\n    color: aliceblue;\r\n    margin-left: 20px;\r\n    margin-bottom: 20px;\r\n    transition: all 3.5s;\r\n    }\r\n\r\n  .drums{\r\n      padding: 20%;\r\n  }\r\n  .playing\r\n  {\r\n      transform: scale(1.1);\r\n      border-color: orange;\r\n  }\r\n","js":"\n        var reloadCSS = require('_css_loader');\n        module.hot.dispose(reloadCSS);\n        module.hot.accept(reloadCSS);\n      "},"hash":"aae3522f8cebf4aa0c849226fbb75246"}